scape/__init__.py
scape/function.py
scape/loss.py
scape/model.py
scape/train.py
scape_sc-0.5.2.dist-info/LICENSE
scape_sc-0.5.2.dist-info/METADATA
scape_sc-0.5.2.dist-info/WHEEL
scape_sc-0.5.2.dist-info/top_level.txt
scape_sc-0.5.2.dist-info/RECORD
