Metadata-Version: 2.1
Name: scape-sc
Version: 0.5.2
Summary: Single-Cell data Analysis via Perturbation Estimation
Author-email: Yuzhe Li <liyuzhezju@gmail.com>
Project-URL: Homepage, https://github.com/ericli0419/SCAPE
Project-URL: Bug Tracker, https://github.com/ericli0419/SCAPE/issues
Classifier: Programming Language :: Python :: 3
Classifier: License :: OSI Approved :: MIT License
Classifier: Operating System :: OS Independent
Classifier: Development Status :: 4 - Beta
Classifier: Intended Audience :: Science/Research
Classifier: Topic :: Scientific/Engineering :: Bio-Informatics
Requires-Python: >3.6.0
License-File: LICENSE
Requires-Dist: build
Requires-Dist: packaging
Requires-Dist: pyparsing
Requires-Dist: tomli
Requires-Dist: numpy
Requires-Dist: pandas
Requires-Dist: scipy
Requires-Dist: scikit-learn
Requires-Dist: scanpy (>=1.4.5)
Requires-Dist: tqdm (>=4.28.1)
Requires-Dist: leidenalg (>=0.8.3)
Requires-Dist: scvelo (>=0.2.4)
